lastpassIndia.py
lastpassIndia-1.1.dist-info/METADATA
lastpassIndia-1.1.dist-info/WHEEL
lastpassIndia-1.1.dist-info/top_level.txt
lastpassIndia-1.1.dist-info/RECORD
